har2csp/__init__.py
har2csp/main.py
har2csp-1.0.0.dist-info/LICENSE
har2csp-1.0.0.dist-info/METADATA
har2csp-1.0.0.dist-info/WHEEL
har2csp-1.0.0.dist-info/entry_points.txt
har2csp-1.0.0.dist-info/top_level.txt
har2csp-1.0.0.dist-info/RECORD
