Metadata-Version: 2.1
Name: har2csp
Version: 1.0.0
Summary: A library to generate CSP headers from HAR files
Home-page: https://github.com/johngrimes/har2csp
Author: John Grimes
Author-email: john@grimes.id.au
Classifier: Development Status :: 3 - Alpha
Classifier: Intended Audience :: Developers
Classifier: License :: OSI Approved :: MIT License
Classifier: Programming Language :: Python :: 3
Classifier: Programming Language :: Python :: 3.6
Classifier: Programming Language :: Python :: 3.7
Classifier: Programming Language :: Python :: 3.8
Classifier: Programming Language :: Python :: 3.9
Classifier: Programming Language :: Python :: 3.10
Classifier: Programming Language :: Python :: 3.11
License-File: LICENSE
